{
   "source" : "http://en.wikipedia.org/wiki/Timeline_of_space_exploration",
   "entries" : [
      {
         "Country/Organization" : "Nazi Germany",
         "Mission Achievements" : "First vehicle to reach 62 mi (100 km) from the Earth's surface (boundary of space)",
         "Mission Name" : "V2 rocket, military program",
         "Date" : "03-Oct-1942"
      },
      {
         "Country/Organization" : "United States",
         "Mission Achievements" : "First space research flight (cosmic radiation experiments)",
         "Mission Name" : "captured and improved V2 rocket",
         "Date" : "10-May-1946"
      },
      {
         "Country/Organization" : "United States",
         "Mission Achievements" : "First U.S.-designed rocket to reach edge of space (80 km (49 mi))",
         "Mission Name" : "Wac Corporal",
         "Date" : "22-May-1946"
      },
      {
         "Country/Organization" : "United States",
         "Mission Achievements" : "First pictures of earth from 62 mi(100 km)",
         "Mission Name" : "V2",
         "Date" : "10-Oct-1946"
      },
      {
         "Country/Organization" : "USA (ABMA)",
         "Mission Achievements" : "First animals in space (fruit flies)",
         "Mission Name" : "V2",
         "Date" : "1947"
      },
      {
         "Country/Organization" : "USSR",
         "Mission Achievements" : "First intercontinental ballistic missile (ICBM)",
         "Mission Name" : "R-7 Semyorka/SS-6 Sapwood",
         "Date" : "21-Aug-1957"
      },
      {
         "Country/Organization" : "USSR",
         "Mission Achievements" : "First artificial satellite",
         "Mission Name" : "Sputnik 1",
         "Date" : "04-Oct-1957"
      },
      {
         "Country/Organization" : "USSR",
         "Mission Achievements" : "First signals from space",
         "Mission Name" : "Sputnik 1",
         "Date" : "04-Oct-1957"
      },
      {
         "Country/Organization" : "USSR",
         "Mission Achievements" : "First animal in orbit, the dog Laika",
         "Mission Name" : "Sputnik 2",
         "Date" : "03-Nov-1957"
      },
      {
         "Country/Organization" : "USA (ABMA)",
         "Mission Achievements" : "Confirmed the existence of the Van Allen belts",
         "Mission Name" : "Explorer 1",
         "Date" : "31-Jan-1958"
      },
      {
         "Country/Organization" : "USSR",
         "Mission Achievements" : "First firing of a rocket in Earth orbit",
         "Mission Name" : "Luna 1",
         "Date" : "02-Jan-1959"
      },
      {
         "Country/Organization" : "USSR",
         "Mission Achievements" : "First reaching Earth escape velocity",
         "Mission Name" : "Luna 1",
         "Date" : "02-Jan-1959"
      },
      {
         "Country/Organization" : "USSR",
         "Mission Achievements" : "First detection of solar wind",
         "Mission Name" : "Luna 1",
         "Date" : "02-Jan-1959"
      },
      {
         "Country/Organization" : "USSR",
         "Mission Achievements" : "First man-made object in heliocentric orbit",
         "Mission Name" : "Luna 1",
         "Date" : "04-Jan-1959"
      },
      {
         "Country/Organization" : "USA (NASA)",
         "Mission Achievements" : "First photograph of Earth from orbit",
         "Mission Name" : "Explorer 6",
         "Date" : "07-Aug-1959"
      },
      {
         "Country/Organization" : "USSR",
         "Mission Achievements" : "First impact into another world (the Moon)",
         "Mission Name" : "Luna 2",
         "Date" : "13-Sep-1959"
      },
      {
         "Country/Organization" : "USSR",
         "Mission Achievements" : "First delivery of national (USSR) pennants in a celestial body",
         "Mission Name" : "Luna 2",
         "Date" : "13-Sep-1959"
      },
      {
         "Country/Organization" : "USSR",
         "Mission Achievements" : "First photos of far side of the Moon",
         "Mission Name" : "Luna 3",
         "Date" : "04-Oct-1959"
      },
      {
         "Country/Organization" : "USSR",
         "Mission Achievements" : "First plants and animals to return alive from Earth orbit",
         "Mission Name" : "Sputnik 5",
         "Date" : "August 19, 1960"
      },
      {
         "Country/Organization" : "USSR",
         "Mission Achievements" : "First launch from orbit[clarification needed]",
         "Mission Name" : "Venera 1",
         "Date" : "1961"
      },
      {
         "Country/Organization" : "USSR",
         "Mission Achievements" : "First mid-course corrections",
         "Mission Name" : "Venera 1",
         "Date" : "1961"
      },
      {
         "Country/Organization" : "USSR",
         "Mission Achievements" : "First spin-stabilisation",
         "Mission Name" : "Venera 1",
         "Date" : "1961"
      },
      {
         "Country/Organization" : "USSR",
         "Mission Achievements" : "First manned spaceflight (Yuri Gagarin)",
         "Mission Name" : "Vostok 1",
         "Date" : "12-Apr-1961"
      },
      {
         "Country/Organization" : "USSR",
         "Mission Achievements" : "First manned orbital flight",
         "Mission Name" : "Vostok 1",
         "Date" : "12-Apr-1961"
      },
      {
         "Country/Organization" : "USA (NASA)",
         "Mission Achievements" : "First orbital solar observatory",
         "Mission Name" : "OSO-1",
         "Date" : "07-Mar-1962"
      },
      {
         "Country/Organization" : "USA (NASA)",
         "Mission Achievements" : "First planetary flyby (Venus closest approach 34,773 kilometers)",
         "Mission Name" : "Mariner 2",
         "Date" : "14-Dec-1962"
      },
      {
         "Country/Organization" : "USSR",
         "Mission Achievements" : "First woman in space (Valentina Tereshkova)",
         "Mission Name" : "Vostok 6",
         "Date" : "16-Jun-1963"
      },
      {
         "Country/Organization" : "USA (NASA)",
         "Mission Achievements" : "First reusable manned spacecraft (suborbital)",
         "Mission Name" : "X-15 Flight 90",
         "Date" : "19-Jul-1963"
      },
      {
         "Country/Organization" : "USSR",
         "Mission Achievements" : "First extra-vehicular activity",
         "Mission Name" : "Voskhod 2",
         "Date" : "18-Mar-1965"
      },
      {
         "Country/Organization" : "USA (NASA)",
         "Mission Achievements" : "First Mars flyby (closest approach 9,846 kilometers)",
         "Mission Name" : "Mariner 4",
         "Date" : "14-Jul-1965"
      },
      {
         "Country/Organization" : "USA (NASA)",
         "Mission Achievements" : "First orbital rendezvous (parallel flight, no docking)",
         "Mission Name" : "Gemini 6A/Gemini 7",
         "Date" : "15-Dec-1965"
      },
      {
         "Country/Organization" : "USSR",
         "Mission Achievements" : "First soft landing on another world (the Moon)",
         "Mission Name" : "Luna 9",
         "Date" : "03-Feb-1966"
      },
      {
         "Country/Organization" : "USSR",
         "Mission Achievements" : "First photos from another world",
         "Mission Name" : "Luna 9",
         "Date" : "03-Feb-1966"
      },
      {
         "Country/Organization" : "USSR",
         "Mission Achievements" : "First impact into another planet (Venus)",
         "Mission Name" : "Venera 3",
         "Date" : "01-Mar-1966"
      },
      {
         "Country/Organization" : "USA (NASA)",
         "Mission Achievements" : "First orbital rendezvous (docking)",
         "Mission Name" : "Gemini 8/Agena target vehicle",
         "Date" : "16-Mar-1966"
      },
      {
         "Country/Organization" : "USSR",
         "Mission Achievements" : "First artificial satellite around another world (the Moon)",
         "Mission Name" : "Luna 10",
         "Date" : "03-Apr-1966"
      },
      {
         "Country/Organization" : "USSR",
         "Mission Achievements" : "First automated (unmanned) docking",
         "Mission Name" : "Cosmos 186/Cosmos 188",
         "Date" : "30-Oct-1967"
      },
      {
         "Country/Organization" : "USA (NASA)",
         "Mission Achievements" : "First orbital ultraviolet observatory",
         "Mission Name" : "OAO-2",
         "Date" : "07-Dec-1968"
      },
      {
         "Country/Organization" : "USA (NASA)",
         "Mission Achievements" : "First human orbiting of another celestial body (Moon)",
         "Mission Name" : "Apollo 8",
         "Date" : "21-Dec-1968"
      },
      {
         "Country/Organization" : "USA (NASA)",
         "Mission Achievements" : "First human on the Moon and first space launch from a celestial body",
         "Mission Name" : "Apollo 11",
         "Date" : "21-Jul-1969"
      },
      {
         "Country/Organization" : "USA (NASA)",
         "Mission Achievements" : "First rendezvous on the surface of a celestial body",
         "Mission Name" : "Apollo 12/Surveyor 3",
         "Date" : "19-Nov-1969"
      },
      {
         "Country/Organization" : "USSR",
         "Mission Achievements" : "First automatic sample return from the Moon",
         "Mission Name" : "Luna 16",
         "Date" : "24-Sep-1970"
      },
      {
         "Country/Organization" : "USSR",
         "Mission Achievements" : "First lunar rover",
         "Mission Name" : "Lunokhod 1",
         "Date" : "23-Nov-1970"
      },
      {
         "Country/Organization" : "USA (NASA)",
         "Mission Achievements" : "First X-ray orbital observatory",
         "Mission Name" : "Uhuru (satellite)",
         "Date" : "12-Dec-1970"
      },
      {
         "Country/Organization" : "USSR",
         "Mission Achievements" : "First soft landing on another planet (Venus)",
         "Mission Name" : "Venera 7",
         "Date" : "15-Dec-1970"
      },
      {
         "Country/Organization" : "USSR",
         "Mission Achievements" : "First signals from another planet",
         "Mission Name" : "Venera 7",
         "Date" : "15-Dec-1970"
      },
      {
         "Country/Organization" : "USSR",
         "Mission Achievements" : "First space station",
         "Mission Name" : "Salyut 1",
         "Date" : "23-Apr-1971"
      },
      {
         "Country/Organization" : "USSR",
         "Mission Achievements" : "First Manned orbital observatory",
         "Mission Name" : "Orion 1",
         "Date" : "June, 1971"
      },
      {
         "Country/Organization" : "USA (NASA)",
         "Mission Achievements" : "First to maintain orbit around another planet (Mars)",
         "Mission Name" : "Mariner 9",
         "Date" : "14-Nov-1971"
      },
      {
         "Country/Organization" : "USSR",
         "Mission Achievements" : "First impact into Mars",
         "Mission Name" : "Mars 2",
         "Date" : "27-Nov-1971"
      },
      {
         "Country/Organization" : "USSR",
         "Mission Achievements" : "First soft Mars landing",
         "Mission Name" : "Mars 3",
         "Date" : "02-Dec-1971"
      },
      {
         "Country/Organization" : "USSR",
         "Mission Achievements" : "First signals from Mars surface",
         "Mission Name" : "Mars 3",
         "Date" : "02-Dec-1971"
      },
      {
         "Country/Organization" : "USA (NASA)",
         "Mission Achievements" : "First human made object sent on escape trajectory away from the Sun",
         "Mission Name" : "Pioneer 10",
         "Date" : "03-Mar-1972"
      },
      {
         "Country/Organization" : "USA (NASA)",
         "Mission Achievements" : "First mission to enter the asteroid belt and leave inner solar system",
         "Mission Name" : "Pioneer 10",
         "Date" : "15-Jul-1972"
      },
      {
         "Country/Organization" : "USA (NASA)",
         "Mission Achievements" : "First orbital gamma ray observatory",
         "Mission Name" : "SAS 2",
         "Date" : "15-Nov-1972"
      },
      {
         "Country/Organization" : "USA (NASA)",
         "Mission Achievements" : "First Jupiter flyby (at 130,000 km). First spacecraft to pass through the asteroid belt.",
         "Mission Name" : "Pioneer 10",
         "Date" : "03-Dec-1973"
      },
      {
         "Country/Organization" : "USA (NASA)",
         "Mission Achievements" : "Venus flyby at 5768 kilometers, first gravitational assist manoeuvre",
         "Mission Name" : "Mariner 10",
         "Date" : "05-Feb-1974"
      },
      {
         "Country/Organization" : "USA (NASA)",
         "Mission Achievements" : "First Mercury flyby at 703 kilometers",
         "Mission Name" : "Mariner 10",
         "Date" : "29-Mar-1974"
      },
      {
         "Country/Organization" : "USSR  USA (NASA)",
         "Mission Achievements" : "First multinational manned mission",
         "Mission Name" : "Apollo-Soyuz Test Project",
         "Date" : "15-Jul-1975"
      },
      {
         "Country/Organization" : "USSR",
         "Mission Achievements" : "First orbit around Venus",
         "Mission Name" : "Venera 9",
         "Date" : "20-Oct-1975"
      },
      {
         "Country/Organization" : "USSR",
         "Mission Achievements" : "First photos from the surface of another planet (Venus)",
         "Mission Name" : "Venera 9",
         "Date" : "22-Oct-1975"
      },
      {
         "Country/Organization" : "USA (NASA)",
         "Mission Achievements" : "First photos and soil samples from the surface of Mars",
         "Mission Name" : "Viking Lander",
         "Date" : "20-Jul-1976"
      },
      {
         "Country/Organization" : "USA (NASA)  ESA UK-SERC",
         "Mission Achievements" : "First real time remotely operated ultraviolet orbital observatory",
         "Mission Name" : "International Ultraviolet Explorer",
         "Date" : "26-Jan-1978"
      },
      {
         "Country/Organization" : "USA (NASA)",
         "Mission Achievements" : "First Saturn flyby at 21,000 km",
         "Mission Name" : "Pioneer 11",
         "Date" : "1 September 1979,"
      },
      {
         "Country/Organization" : "USA (NASA)",
         "Mission Achievements" : "First Reusable manned spacecraft (orbital)",
         "Mission Name" : "STS-1",
         "Date" : "12-Apr-1981"
      },
      {
         "Country/Organization" : "USSR",
         "Mission Achievements" : "First Venus soil samples & sound recording of another world",
         "Mission Name" : "Venera 13",
         "Date" : "01-Mar-1982"
      },
      {
         "Country/Organization" : "USA (NASA)  UK-SERC Netherlands-NIVR",
         "Mission Achievements" : "First Infrared orbital observatory",
         "Mission Name" : "IRAS",
         "Date" : "25-Jan-1983"
      },
      {
         "Country/Organization" : "USSR  France",
         "Mission Achievements" : "Ultraviolet orbital observatory",
         "Mission Name" : "Astron",
         "Date" : "23-Mar-1983"
      },
      {
         "Country/Organization" : "USA (NASA)",
         "Mission Achievements" : "First spacecraft beyond the orbit of Neptune (first spacecraft to pass beyond all Solar System planets)",
         "Mission Name" : "Pioneer 10",
         "Date" : "13-Jun-1983"
      },
      {
         "Country/Organization" : "USA (NASA)",
         "Mission Achievements" : "First Uranus flyby (closest approach 81,500 kilometers)",
         "Mission Name" : "Voyager 2",
         "Date" : "24-Jan-1986"
      },
      {
         "Country/Organization" : "USSR",
         "Mission Achievements" : "First consistently inhabited long-term research space station",
         "Mission Name" : "Mir",
         "Date" : "19-Feb-1986"
      },
      {
         "Country/Organization" : "USA (NASA)",
         "Mission Achievements" : "First Neptune flyby",
         "Mission Name" : "Voyager 2",
         "Date" : "25-Aug-1989"
      },
      {
         "Country/Organization" : "USA (NASA)",
         "Mission Achievements" : "First orbital cosmic microwave observatory",
         "Mission Name" : "COBE",
         "Date" : "18-Nov-1989"
      },
      {
         "Country/Organization" : "USSR  France  Denmark  Bulgaria",
         "Mission Achievements" : "Ultraviolet to gamma ray spectrum orbital observatory",
         "Mission Name" : "Granat",
         "Date" : "01-Dec-1989"
      },
      {
         "Country/Organization" : "USA (NASA)",
         "Mission Achievements" : "First photograph of the whole solar system",
         "Mission Name" : "Voyager 1",
         "Date" : "14-Feb-1990"
      },
      {
         "Country/Organization" : "USA (NASA)  ESA",
         "Mission Achievements" : "Optical orbital observatory",
         "Mission Name" : "Hubble Space Telescope",
         "Date" : "24-Apr-1990"
      },
      {
         "Country/Organization" : "USA (NASA)",
         "Mission Achievements" : "First asteroid flyby (951 Gaspra closest approach 1,600 kilometers)",
         "Mission Name" : "Galileo",
         "Date" : "21-Oct-1991"
      },
      {
         "Country/Organization" : "USA (NASA)  ESA",
         "Mission Achievements" : "First polar orbit around the Sun",
         "Mission Name" : "Ulysses",
         "Date" : "08-Feb-1992"
      },
      {
         "Country/Organization" : "USA (NASA)",
         "Mission Achievements" : "First orbit of Jupiter",
         "Mission Name" : "Galileo",
         "Date" : "07-Dec-1995"
      },
      {
         "Country/Organization" : "USA (NASA)",
         "Mission Achievements" : "First mission into the atmosphere of a gas giant (Jupiter)",
         "Mission Name" : "Galileo's atmospheric entry probe",
         "Date" : "07-Dec-1995"
      },
      {
         "Country/Organization" : "USA (NASA)",
         "Mission Achievements" : "First orbiting of an asteroid (433 Eros)",
         "Mission Name" : "NEAR Shoemaker",
         "Date" : "14-Feb-2000"
      },
      {
         "Country/Organization" : "USA (NASA)",
         "Mission Achievements" : "First landing on an asteroid (433 Eros)",
         "Mission Name" : "NEAR Shoemaker",
         "Date" : "12-Feb-2001"
      },
      {
         "Country/Organization" : "USA (NASA)",
         "Mission Achievements" : "Free ranging Mars rover",
         "Mission Name" : "Spirit rover",
         "Date" : "04-Jan-2004"
      },
      {
         "Country/Organization" : "USA (NASA)",
         "Mission Achievements" : "Free ranging Mars rover",
         "Mission Name" : "Opportunity rover",
         "Date" : "25-Jan-2004"
      },
      {
         "Country/Organization" : "USA (NASA)  ESA  ASI",
         "Mission Achievements" : "First orbit of Saturn",
         "Mission Name" : "Cassini_Huygens",
         "Date" : "01-Jul-2004"
      },
      {
         "Country/Organization" : "ESA  USA (NASA)  ASI",
         "Mission Achievements" : "First soft landing on Titan",
         "Mission Name" : "Cassini_Huygens",
         "Date" : "14-Jan-2005"
      },
      {
         "Country/Organization" : "China",
         "Mission Achievements" : "First stage of the country's lunar probe program , the satellite Chang'e I",
         "Mission Name" : "Chang'e I",
         "Date" : "24-Oct-2007"
      },
      {
         "Country/Organization" : "USA",
         "Mission Achievements" : "Kepler Mission is launched, first space telescope designated to search for Earth-like exoplanets",
         "Mission Name" : "Kepler Mission",
         "Date" : "06-Mar-2009"
      }
   ]
}
